mcp_server_macos_defaults/__init__.py
mcp_server_macos_defaults/server.py
mcp_server_macos_defaults-0.1.2.dist-info/METADATA
mcp_server_macos_defaults-0.1.2.dist-info/WHEEL
mcp_server_macos_defaults-0.1.2.dist-info/entry_points.txt
mcp_server_macos_defaults-0.1.2.dist-info/RECORD
