Metadata-Version: 2.3
Name: mcp-server-macos-defaults
Version: 0.1.2
Summary: MCP server for reading/writing macOS defaults (settings)
Author-email: Wes Higbee <wes.mcclure@gmail.com>
Requires-Python: >=3.13
Requires-Dist: mcp>=1.0.0
